{
  "$schema": "https://github.com/tauri-apps/tauri/blob/dev/.schema/config.schema.json",
  "build": {
    "beforeDevCommand": "npm run dev",
    "beforeBuildCommand": "npm run build",
    "devPath": "http://localhost:5173",
    "distDir": "../dist",
    "withGlobalTauri": false
  },
  "package": {
    "productName": "Jukebox",
    "version": "0.1.0"
  },
  "tauri": {
    "allowlist": {
      "all": false,
      "shell": {
        "all": false,
        "open": true
      },
      "window": {
        "all": false,
        "close": true,
        "hide": true,
        "show": true,
        "maximize": true,
        "minimize": true,
        "unmaximize": true,
        "unminimize": true,
        "startDragging": true
      },
      "notification": {
        "all": true
      }
    },
    "bundle": {
      "active": true,
      "category": "Music",
      "copyright": "",
      "deb": {
        "depends": []
      },
      "externalBin": [],
      "icon": [
        "icons/32x32.png",
        "icons/128x128.png",
        "icons/128x128@2x.png",
        "icons/icon.icns",
        "icons/icon.ico"
      ],
      "identifier": "com.jukebox.player",
      "longDescription": "Modern Jukebox Player with macOS Media Controls Integration",
      "macOS": {
        "entitlements": null,
        "exceptionDomain": "",
        "frameworks": [],
        "providerShortName": null,
        "signingIdentity": null,
        "minimumSystemVersion": "10.13"
      },
      "resources": [],
      "shortDescription": "Jukebox Player",
      "targets": "all",
      "windows": {
        "certificateThumbprint": null,
        "digestAlgorithm": "sha256",
        "timestampUrl": ""
      }
    },
    "security": {
      "csp": null
    },
    "systemTray": {
      "iconPath": "icons/icon.png",
      "iconAsTemplate": true,
      "menuOnLeftClick": true
    },
    "updater": {
      "active": false
    },
    "windows": [
      {
        "fullscreen": false,
        "height": 800,
        "resizable": true,
        "title": "Jukebox — Web Player",
        "width": 1400,
        "minWidth": 800,
        "minHeight": 600,
        "center": true,
        "decorations": true,
        "transparent": false,
        "alwaysOnTop": false,
        "skipTaskbar": false
      }
    ],
    "macOSPrivateApi": true
  }
}
